imgcomposer/__init__.py
imgcomposer/codeimg.py
imgcomposer/datamatrix.py
imgcomposer/qrcode.py
imgcomposer/scripts.py
imgcomposer/upca.py
barcode_image_composer-1.0.0.dist-info/LICENSE
barcode_image_composer-1.0.0.dist-info/METADATA
barcode_image_composer-1.0.0.dist-info/WHEEL
barcode_image_composer-1.0.0.dist-info/entry_points.txt
barcode_image_composer-1.0.0.dist-info/top_level.txt
barcode_image_composer-1.0.0.dist-info/RECORD
